pixelzyodi/__init__.py
pixelzyodi/main.py
pixelzyodi-0.3.3.dist-info/LICENSE
pixelzyodi-0.3.3.dist-info/METADATA
pixelzyodi-0.3.3.dist-info/WHEEL
pixelzyodi-0.3.3.dist-info/top_level.txt
pixelzyodi-0.3.3.dist-info/RECORD
