Metadata-Version: 2.1
Name: pixelzyodi
Version: 0.3.3
License-File: LICENSE
